ais/__init__.py
ais/agent.py
ais/auth.py
ais/client.py
ais/constants.py
ais/exceptions.py
ais/message.py
ais/observability.py
ais/transport.py
ais/validation.py
ais_protocol-0.1.3.dist-info/licenses/LICENSE
ais_protocol-0.1.3.dist-info/METADATA
ais_protocol-0.1.3.dist-info/WHEEL
ais_protocol-0.1.3.dist-info/top_level.txt
ais_protocol-0.1.3.dist-info/RECORD
