Metadata-Version: 2.4
Name: ais-protocol
Version: 0.1.3
Summary: Agent Interface Standard - A protocol for AI agent-to-agent communication
Author-email: Mercola Consulting Services <manishk@mercola.com>
Maintainer-email: Mercola Consulting Services <manishk@mercola.com>
License: Apache-2.0
Project-URL: Homepage, https://github.com/ais-protocol/ais-python
Project-URL: Documentation, https://docs.ais-protocol.org
Project-URL: Repository, https://github.com/ais-protocol/ais-python
Project-URL: Issues, https://github.com/ais-protocol/ais-python/issues
Keywords: ai,agents,protocol,multi-agent,communication
Classifier: Development Status :: 3 - Alpha
Classifier: Intended Audience :: Developers
Classifier: License :: OSI Approved :: Apache Software License
Classifier: Programming Language :: Python :: 3
Classifier: Programming Language :: Python :: 3.9
Classifier: Programming Language :: Python :: 3.10
Classifier: Programming Language :: Python :: 3.11
Classifier: Programming Language :: Python :: 3.12
Requires-Python: >=3.9
License-File: LICENSE
Requires-Dist: aiohttp>=3.9.0
Requires-Dist: pydantic>=2.0.0
Requires-Dist: python-dateutil>=2.8.0
Requires-Dist: jsonschema>=4.20.0
Requires-Dist: PyJWT>=2.8.0
Provides-Extra: dev
Requires-Dist: pytest>=7.4.0; extra == "dev"
Requires-Dist: pytest-asyncio>=0.21.0; extra == "dev"
Requires-Dist: pytest-cov>=4.1.0; extra == "dev"
Requires-Dist: black>=23.0.0; extra == "dev"
Requires-Dist: mypy>=1.7.0; extra == "dev"
Requires-Dist: ruff>=0.1.0; extra == "dev"
Dynamic: license-file
